config_manager/__init__.py
config_manager/composite.py
config_manager/helper.py
config_manager/parser.py
config_manager/registry.py
modern_config_manager-0.3.2.dist-info/LICENSE
modern_config_manager-0.3.2.dist-info/METADATA
modern_config_manager-0.3.2.dist-info/WHEEL
modern_config_manager-0.3.2.dist-info/top_level.txt
modern_config_manager-0.3.2.dist-info/RECORD
